Workbook

Sheet Unit Economics
B1: Story Mode — Unit Economics Model
B2: All costs based on OpenRouter → Claude 3.5 Haiku pricing
B4: AI PRICING ASSUMPTIONS | E4: Source: spendTracker.ts
C5: Rate | D5: Unit
B6: Input token cost | C6: 0.0008 | D6: per 1K tokens
B7: Output token cost | C7: 0.004 | D7: per 1K tokens
B9: PER-PAGE TOKEN ESTIMATES
B10: Component | C10: Tokens | D10: Notes
B11: System prompt | C11: 1000 | D11: Guide personality + rules
B12: Game state | C12: 500 | D12: Character, quests, inventory
B13: Rolling summary | C13: 600 | D13: After first 10 pages
B14: Recent messages (5) | C14: 1500 | D14: ~300 tokens each
B15: Player input | C15: 50 | D15: Choice selection
B16: Total input per page | C16: =SUM(C11:C15) -> 3650
B17: Output per page (narrative + choices) | C17: 650
B19: COST PER PAGE
B20: Input cost per page | C20: =C16/1000*C6 -> 0.00292
B21: Output cost per page | C21: =C17/1000*C7 -> 0.0026
B22: Total cost per page | C22: =C20+C21 -> 0.00552
B24: SUMMARIZATION COST
B25: Summarization trigger interval | C25: 10 | D25: pages
B26: Summarization input tokens | C26: 2500
B27: Summarization output tokens | C27: 600
B28: Cost per summarization | C28: =C26/1000*C6+C27/1000*C7 -> 0.0044
B30: COST PER STORY BY LENGTH
B31: Format | C31: Pages | D31: Page Cost | E31: Summarizations | F31: Summary Cost | G31: Total Cost
B32: Short Story | C32: 25 | D32: =C32*$C$22 -> 0.138 | E32: =ROUNDDOWN(C32/$C$25,0) -> 2 | F32: =E32*$C$28 -> 0.0088 | G32: =D32+F32 -> 0.1468
B33: Novella | C33: 50 | D33: =C33*$C$22 -> 0.276 | E33: =ROUNDDOWN(C33/$C$25,0) -> 5 | F33: =E33*$C$28 -> 0.022 | G33: =D33+F33 -> 0.298
B34: Novel | C34: 100 | D34: =C34*$C$22 -> 0.552 | E34: =ROUNDDOWN(C34/$C$25,0) -> 10 | F34: =E34*$C$28 -> 0.044 | G34: =D34+F34 -> 0.596
B35: Epic | C35: 250 | D35: =C35*$C$22 -> 1.38 | E35: =ROUNDDOWN(C35/$C$25,0) -> 25 | F35: =E35*$C$28 -> 0.11 | G35: =D35+F35 -> 1.49
B38: SONNET UPGRADE COMPARISON | E38: If upgrading AI model for premium tier
B39: Sonnet input cost (per 1K) | C39: 0.003
B40: Sonnet output cost (per 1K) | C40: 0.015
B41: Sonnet cost per page | C41: =C16/1000*C39+C17/1000*C40 -> 0.0207
B42: Sonnet multiplier vs Haiku | C42: =C41/C22 -> 3.75
B44: Format | C44: Haiku Cost | D44: Sonnet Cost | E44: Difference
B45: Short Story | C45: =G32 -> 0.1468 | D45: =C32*C41+E32*(C26/1000*C39+C27/1000*C40) -> 0.5505 | E45: =D45-C45 -> 0.4037
B46: Novella | C46: =G33 -> 0.298 | D46: =C33*C41+E33*(C26/1000*C39+C27/1000*C40) -> 1.1175 | E46: =D46-C46 -> 0.8195
B47: Novel | C47: =G34 -> 0.596 | D47: =C34*C41+E34*(C26/1000*C39+C27/1000*C40) -> 2.235 | E47: =D47-C47 -> 1.639
B48: Epic | C48: =G35 -> 1.49 | D48: =C35*C41+E35*(C26/1000*C39+C27/1000*C40) -> 5.5875 | E48: =D48-C48 -> 4.0975

Sheet Subscription Tiers
B1: Story Mode — Subscription Tiers & Margins
B3: TIER DEFINITIONS
B4: Tier | C4: Monthly Price | D4: Pages/Month | E4: AI Model | F4: Community | G4: Cross-Story
B5: Free | C5: 0 | D5: 50 | E5: Haiku | F5: Browse only | G5: No
B6: Storyteller | C6: 5 | D6: 300 | E6: Haiku | F6: Vote + Nominate | G6: Yes
B7: Author | C7: 10 | D7: 1000 | E7: Haiku + Sonnet | F7: Full access | G7: Yes + 4th wall
B9: COST PER SUBSCRIBER (HEAVY USAGE)
B10: Tier | C10: Pages Used | D10: Summarizations | E10: AI Cost | F10: Revenue | G10: Gross Margin | H10: Margin %
B11: =B5 -> Free | C11: =D5 -> 50 | D11: =ROUNDDOWN(C11/'Unit Economics'!$C$25,0) -> 5 | E11: =C11*'Unit Economics'!$C$22+D11*'Unit Economics'!$C$28 -> 0.298 | F11: =C5 -> 0 | G11: =F11-E11 -> -0.298 | H11: =IF(F11=0,"-",G11/F11) -> -
B12: =B6 -> Storyteller | C12: =D6 -> 300 | D12: =ROUNDDOWN(C12/'Unit Economics'!$C$25,0) -> 30 | E12: =C12*'Unit Economics'!$C$22+D12*'Unit Economics'!$C$28 -> 1.788 | F12: =C6 -> 5 | G12: =F12-E12 -> 3.212 | H12: =IF(F12=0,"-",G12/F12) -> 0.6424
B13: =B7 -> Author | C13: =D7 -> 1000 | D13: =ROUNDDOWN(C13/'Unit Economics'!$C$25,0) -> 100 | E13: =C13*'Unit Economics'!$C$41+D13*('Unit Economics'!C26/1000*'Unit Economics'!C39+'Unit Economics'!C27/1000*'Unit Economics'!C40) -> 22.35 | F13: =C7 -> 10 | G13: =F13-E13 -> -12.35 | H13: =IF(F13=0,"-",G13/F13) -> -1.235
B15: COST PER SUBSCRIBER (AVERAGE USAGE) | F15: Most users won't hit limits
B16: Tier | C16: Avg Pages/Mo | D16: Summarizations | E16: AI Cost | F16: Revenue | G16: Gross Margin | H16: Margin %
B17: =B5 -> Free | C17: 20 | D17: =ROUNDDOWN(C17/'Unit Economics'!$C$25,0) -> 2 | E17: =C17*'Unit Economics'!$C$22+D17*'Unit Economics'!$C$28 -> 0.1192 | F17: =C5 -> 0 | G17: =F17-E17 -> -0.1192 | H17: =IF(F17=0,"-",G17/F17) -> -
B18: =B6 -> Storyteller | C18: 120 | D18: =ROUNDDOWN(C18/'Unit Economics'!$C$25,0) -> 12 | E18: =C18*'Unit Economics'!$C$22+D18*'Unit Economics'!$C$28 -> 0.7152 | F18: =C6 -> 5 | G18: =F18-E18 -> 4.2848 | H18: =IF(F18=0,"-",G18/F18) -> 0.85696
B19: =B7 -> Author | C19: 400 | D19: =ROUNDDOWN(C19/'Unit Economics'!$C$25,0) -> 40 | E19: =C19*'Unit Economics'!$C$41+D19*('Unit Economics'!C26/1000*'Unit Economics'!C39+'Unit Economics'!C27/1000*'Unit Economics'!C40) -> 8.94 | F19: =C7 -> 10 | G19: =F19-E19 -> 1.06 | H19: =IF(F19=0,"-",G19/F19) -> 0.106

Sheet Scaling Scenarios
B1: Story Mode — Scaling Scenarios (Monthly)
B3: FIXED INFRASTRUCTURE (MONTHLY)
B4: Supabase (DB) | C4: 0 | D4: Free tier to ~50K MAU
B5: Render (server) | C5: 7 | D5: Starter plan
B6: Domain + misc | C6: 5
B7: PostHog / Sentry | C7: 0 | D7: Free tiers
B8: Total fixed costs | C8: =SUM(C4:C7) -> 12
B10: MONTHLY P&L SCENARIOS
C12: Soft Launch | D12: Month 3 | E12: Month 6 | F12: Month 12 | G12: Month 18
B13: Free users | C13: 50 | D13: 300 | E13: 1000 | F13: 5000 | G13: 15000
B14: Storyteller ($5) subs | C14: 5 | D14: 30 | E14: 100 | F14: 500 | G14: 2000
B15: Author ($10) subs | C15: 2 | D15: 10 | E15: 40 | F15: 200 | G15: 800
B16: Total users | C16: =C13+C14+C15 -> 57 | D16: =D13+D14+D15 -> 340 | E16: =E13+E14+E15 -> 1140 | F16: =F13+F14+F15 -> 5700 | G16: =G13+G14+G15 -> 17800
B17: Conversion rate | C17: =(C14+C15)/C16 -> 0.12280702 | D17: =(D14+D15)/D16 -> 0.11764706 | E17: =(E14+E15)/E16 -> 0.12280702 | F17: =(F14+F15)/F16 -> 0.12280702 | G17: =(G14+G15)/G16 -> 0.15730337
B19: REVENUE
B20: Storyteller revenue | C20: =C14*'Subscription Tiers'!$C$6 -> 25 | D20: =D14*'Subscription Tiers'!$C$6 -> 150 | E20: =E14*'Subscription Tiers'!$C$6 -> 500 | F20: =F14*'Subscription Tiers'!$C$6 -> 2500 | G20: =G14*'Subscription Tiers'!$C$6 -> 10000
B21: Author revenue | C21: =C15*'Subscription Tiers'!$C$7 -> 20 | D21: =D15*'Subscription Tiers'!$C$7 -> 100 | E21: =E15*'Subscription Tiers'!$C$7 -> 400 | F21: =F15*'Subscription Tiers'!$C$7 -> 2000 | G21: =G15*'Subscription Tiers'!$C$7 -> 8000
B22: Total revenue | C22: =C20+C21 -> 45 | D22: =D20+D21 -> 250 | E22: =E20+E21 -> 900 | F22: =F20+F21 -> 4500 | G22: =G20+G21 -> 18000
B24: AI COSTS
B25: Free user AI cost | C25: =C13*'Subscription Tiers'!$E$17 -> 5.96 | D25: =D13*'Subscription Tiers'!$E$17 -> 35.76 | E25: =E13*'Subscription Tiers'!$E$17 -> 119.2 | F25: =F13*'Subscription Tiers'!$E$17 -> 596 | G25: =G13*'Subscription Tiers'!$E$17 -> 1788
B26: Storyteller AI cost | C26: =C14*'Subscription Tiers'!$E$18 -> 3.576 | D26: =D14*'Subscription Tiers'!$E$18 -> 21.456 | E26: =E14*'Subscription Tiers'!$E$18 -> 71.52 | F26: =F14*'Subscription Tiers'!$E$18 -> 357.6 | G26: =G14*'Subscription Tiers'!$E$18 -> 1430.4
B27: Author AI cost | C27: =C15*'Subscription Tiers'!$E$19 -> 17.88 | D27: =D15*'Subscription Tiers'!$E$19 -> 89.4 | E27: =E15*'Subscription Tiers'!$E$19 -> 357.6 | F27: =F15*'Subscription Tiers'!$E$19 -> 1788 | G27: =G15*'Subscription Tiers'!$E$19 -> 7152
B28: Total AI cost | C28: =C25+C26+C27 -> 27.416 | D28: =D25+D26+D27 -> 146.616 | E28: =E25+E26+E27 -> 548.32 | F28: =F25+F26+F27 -> 2741.6 | G28: =G25+G26+G27 -> 10370.4
B29: Infrastructure cost | C29: =$C$8 -> 12 | D29: =$C$8 -> 12 | E29: =$C$8 -> 12 | F29: =$C$8 -> 12 | G29: =$C$8 -> 12
B31: BOTTOM LINE
B32: Total costs | C32: =C28+C29 -> 39.416 | D32: =D28+D29 -> 158.616 | E32: =E28+E29 -> 560.32 | F32: =F28+F29 -> 2753.6 | G32: =G28+G29 -> 10382.4
B33: Net profit / (loss) | C33: =C22-C32 -> 5.584 | D33: =D22-D32 -> 91.384 | E33: =E22-E32 -> 339.68 | F33: =F22-F32 -> 1746.4 | G33: =G22-G32 -> 7617.6
B34: Gross margin | C34: =IF(C22=0,"-",C33/C22) -> 0.12408889 | D34: =IF(D22=0,"-",D33/D22) -> 0.365536 | E34: =IF(E22=0,"-",E33/E22) -> 0.37742222 | F34: =IF(F22=0,"-",F33/F22) -> 0.38808889 | G34: =IF(G22=0,"-",G33/G22) -> 0.4232
B36: AI cost per user (blended) | C36: =C28/C16 -> 0.48098246 | D36: =D28/D16 -> 0.43122353 | E36: =E28/E16 -> 0.48098246 | F36: =F28/F16 -> 0.48098246 | G36: =G28/G16 -> 0.58260674
B37: Revenue per user (blended) | C37: =C22/C16 -> 0.78947368 | D37: =D22/D16 -> 0.73529412 | E37: =E22/E16 -> 0.78947368 | F37: =F22/F16 -> 0.78947368 | G37: =G22/G16 -> 1.011236

Sheet Launch Strategy
B1: Story Mode — Launch & Community Strategy
B3: PHASE 1: ALPHA (Months 1-2)
B4: Milestone | C4: What Ships | D4: Goal | E4: Users | F4: Monthly Cost
B5: M2: AI Memory | C5: Live-test rolling summary | D5: Verify AI remembers plot | E5: You + Rachel | F5: $0
B6: M3: Page Structure | C6: 25 and 50-page stories | D6: Validate pacing + cost model | E6: 5-10 friends | F6: ~$5
B7: M4: The Guide | C7: Unified AI character voice | D7: Test personality across contexts | E7: Same group | F7: ~$5
B9: PHASE 2: BETA (Months 3-5)
B10: Milestone | C10: What Ships | D10: Goal | E10: Users | F10: Monthly Cost
B11: M5: Bookshelf UI | C11: Full visual redesign from prototype | D11: The 'wow' moment for new users | E11: 50-200 beta | F11: ~$50-100
B12: Production | C12: Error handling, monitoring, Render | D12: Stable enough for strangers | E12: Same | F12: ~$20 infra
B13: Waitlist + Landing | C13: Public signup page | D13: Build anticipation, collect emails | E13: 500+ signups | F13: ~$10
B15: PHASE 3: PUBLIC LAUNCH (Month 6)
B16: Channel | C16: Tactic | D16: Why | E16: Cost | F16: Expected Users
B17: Product Hunt | C17: Launch day campaign | D17: Core early adopter audience | E17: $0 | F17: 500-2000
B18: Reddit | C18: r/interactive, r/writing, r/rpg | D18: Niche communities who want this | E18: $0 | F18: 200-500
B19: TikTok/Reels | C19: Screen recordings of stories | D19: Visual medium, shareable moments | E19: $0-50 | F19: Variable
B20: Indie Hackers | C20: Build-in-public thread | D20: Developer + maker community | E20: $0 | F20: 100-300
B21: Referrals | C21: 'Invite to your story' mechanic | D21: Viral loop built into product | E21: $0 | F21: Multiplier
B23: PHASE 4: COMMUNITY (Months 7-12)
B24: Feature | C24: What It Enables | D24: Retention Lever | E24: Tier Gate
B25: Cross-story travel | C25: Characters move between books | D25: Long-term character investment | E25: Storyteller+
B26: Community templates | C26: Player worlds become playable | D26: Creator economy, recognition | E26: Author
B27: NPC injection | C27: Your character in others' stories | D27: Social connection without multiplayer | E27: Author
B28: Adaptive theming | C28: Stories change visual tone | D28: Immersion, screenshot-worthy | E28: All tiers
B29: Story sharing | C29: Share completed stories publicly | D29: Organic marketing, word of mouth | E29: All tiers
B32: KEY METRICS
B33: Metric | C33: Target | D33: Why It Matters
B34: Story completion rate | C34: >40% | D34: If people finish stories, the page model works
B35: Pages per session | C35: >8 | D35: Engagement depth — are people hooked?
B36: Free → Storyteller conversion | C36: >5% | D36: Core business viability
B37: Storyteller → Author upgrade | C37: >15% | D37: Premium value resonates
B38: D7 retention | C38: >25% | D38: Do people come back after first story?
B39: Stories per user per month | C39: >1.5 | D39: Replay value, not one-and-done
B40: Community template plays | C40: >10 per template | D40: Community flywheel working
B41: AI cost per MAU | C41: <$0.50 | D41: Unit economics sustainable at scale
